{
  "source": "polymarket",
  "event_slug": "world-cup-winner",
  "fetched_at": "2026-06-27T16:16:26.930Z",
  "total_volume_usd": 3260158106.9514303,
  "teams": {
    "ESP": {
      "prob": 0.118,
      "change24h": -0.02,
      "volume": 65182351
    },
    "SUI": {
      "prob": 0.01,
      "change24h": 0.001,
      "volume": 71731538
    },
    "ENG": {
      "prob": 0.102,
      "change24h": null,
      "volume": 59095296
    },
    "FRA": {
      "prob": 0.23,
      "change24h": 0.04,
      "volume": 75291668
    },
    "KOR": {
      "prob": 0.001,
      "change24h": -0.001,
      "volume": 107498242
    },
    "BRA": {
      "prob": 0.057,
      "change24h": 0.001,
      "volume": 59028357
    },
    "ARG": {
      "prob": 0.19,
      "change24h": 0.038,
      "volume": 76673215
    },
    "GER": {
      "prob": 0.04,
      "change24h": -0.007,
      "volume": 68935769
    },
    "COL": {
      "prob": 0.014,
      "change24h": -0.003,
      "volume": 75080562
    },
    "IRN": {
      "prob": 0.001,
      "change24h": null,
      "volume": 61738465
    },
    "POR": {
      "prob": 0.081,
      "change24h": -0.003,
      "volume": 71056092
    },
    "GHA": {
      "prob": 0.002,
      "change24h": null,
      "volume": 66422305
    },
    "NED": {
      "prob": 0.047,
      "change24h": -0.011,
      "volume": 70489001
    },
    "ALG": {
      "prob": 0.001,
      "change24h": null,
      "volume": 73132292
    },
    "BIH": {
      "prob": 0.002,
      "change24h": null,
      "volume": 56740519
    },
    "USA": {
      "prob": 0.023,
      "change24h": -0.007,
      "volume": 106067894
    },
    "CAN": {
      "prob": 0.003,
      "change24h": null,
      "volume": 77588866
    },
    "MEX": {
      "prob": 0.013,
      "change24h": null,
      "volume": 92765080
    },
    "PAR": {
      "prob": 0.001,
      "change24h": -0.001,
      "volume": 73779192
    },
    "SCO": {
      "prob": 0.001,
      "change24h": null,
      "volume": 67935547
    },
    "JPN": {
      "prob": 0.015,
      "change24h": -0.002,
      "volume": 84289684
    },
    "NOR": {
      "prob": 0.025,
      "change24h": -0.007,
      "volume": 73521765
    },
    "ECU": {
      "prob": 0.006,
      "change24h": null,
      "volume": 87530434
    },
    "UZB": {
      "prob": 0.001,
      "change24h": null,
      "volume": 61521949
    },
    "MAR": {
      "prob": 0.015,
      "change24h": -0.002,
      "volume": 80544960
    },
    "RSA": {
      "prob": 0.001,
      "change24h": null,
      "volume": 45086876
    },
    "SEN": {
      "prob": 0.005,
      "change24h": 0.002,
      "volume": 66965987
    },
    "CIV": {
      "prob": 0.003,
      "change24h": -0.001,
      "volume": 98735941
    },
    "COD": {
      "prob": 0.001,
      "change24h": null,
      "volume": 86410259
    },
    "CPV": {
      "prob": 0.001,
      "change24h": -0.001,
      "volume": 81907416
    },
    "BEL": {
      "prob": 0.014,
      "change24h": 0.001,
      "volume": 78157242
    },
    "AUS": {
      "prob": 0.002,
      "change24h": null,
      "volume": 75768350
    },
    "AUT": {
      "prob": 0.002,
      "change24h": -0.001,
      "volume": 72722533
    },
    "CRO": {
      "prob": 0.005,
      "change24h": null,
      "volume": 83156433
    },
    "EGY": {
      "prob": 0.002,
      "change24h": -0.001,
      "volume": 89110585
    },
    "SWE": {
      "prob": 0.002,
      "change24h": -0.001,
      "volume": 65481600
    }
  }
}
