{
  "source": "polymarket",
  "event_slug": "world-cup-winner",
  "fetched_at": "2026-06-30T07:42:01.138Z",
  "total_volume_usd": 3509399710.3004756,
  "teams": {
    "ESP": {
      "prob": 0.113,
      "change24h": 0.002,
      "volume": 71489187
    },
    "SUI": {
      "prob": 0.009,
      "change24h": -0.001,
      "volume": 78176386
    },
    "ENG": {
      "prob": 0.101,
      "change24h": -0.002,
      "volume": 64784526
    },
    "FRA": {
      "prob": 0.29,
      "change24h": 0.055,
      "volume": 81417152
    },
    "BRA": {
      "prob": 0.071,
      "change24h": 0.014,
      "volume": 67898923
    },
    "ARG": {
      "prob": 0.194,
      "change24h": -0.015,
      "volume": 85029249
    },
    "COL": {
      "prob": 0.028,
      "change24h": 0.002,
      "volume": 82142327
    },
    "POR": {
      "prob": 0.06,
      "change24h": -0.002,
      "volume": 82278304
    },
    "GHA": {
      "prob": 0.001,
      "change24h": -0.001,
      "volume": 73593622
    },
    "ALG": {
      "prob": 0.002,
      "change24h": null,
      "volume": 81627277
    },
    "BIH": {
      "prob": 0.001,
      "change24h": null,
      "volume": 62090329
    },
    "USA": {
      "prob": 0.028,
      "change24h": 0.004,
      "volume": 113337642
    },
    "CAN": {
      "prob": 0.003,
      "change24h": null,
      "volume": 90390530
    },
    "MEX": {
      "prob": 0.018,
      "change24h": 0.006,
      "volume": 106273363
    },
    "PAR": {
      "prob": 0.003,
      "change24h": 0.002,
      "volume": 89436471
    },
    "NOR": {
      "prob": 0.02,
      "change24h": null,
      "volume": 79397974
    },
    "ECU": {
      "prob": 0.006,
      "change24h": null,
      "volume": 92598560
    },
    "MAR": {
      "prob": 0.04,
      "change24h": 0.026,
      "volume": 98432232
    },
    "SEN": {
      "prob": 0.005,
      "change24h": null,
      "volume": 71624397
    },
    "CIV": {
      "prob": 0.004,
      "change24h": 0.001,
      "volume": 106337961
    },
    "COD": {
      "prob": 0.001,
      "change24h": null,
      "volume": 89677526
    },
    "CPV": {
      "prob": 0.001,
      "change24h": null,
      "volume": 89384993
    },
    "BEL": {
      "prob": 0.014,
      "change24h": null,
      "volume": 84134280
    },
    "AUS": {
      "prob": 0.002,
      "change24h": null,
      "volume": 78636995
    },
    "AUT": {
      "prob": 0.002,
      "change24h": null,
      "volume": 78440745
    },
    "CRO": {
      "prob": 0.004,
      "change24h": null,
      "volume": 94404753
    },
    "EGY": {
      "prob": 0.002,
      "change24h": null,
      "volume": 92301336
    },
    "SWE": {
      "prob": 0.002,
      "change24h": null,
      "volume": 70495283
    }
  }
}
