{
  "source": "polymarket",
  "event_slug": "world-cup-winner",
  "fetched_at": "2026-06-21T11:17:10.085Z",
  "total_volume_usd": 2810363702.622837,
  "teams": {
    "ESP": {
      "prob": 0.137,
      "change24h": null,
      "volume": 55254539
    },
    "NZL": {
      "prob": 0.001,
      "change24h": null,
      "volume": 47265512
    },
    "SUI": {
      "prob": 0.008,
      "change24h": null,
      "volume": 60729369
    },
    "ENG": {
      "prob": 0.126,
      "change24h": null,
      "volume": 50115072
    },
    "FRA": {
      "prob": 0.198,
      "change24h": 0.006,
      "volume": 65377608
    },
    "KOR": {
      "prob": 0.004,
      "change24h": null,
      "volume": 86926322
    },
    "BRA": {
      "prob": 0.06,
      "change24h": -0.001,
      "volume": 48182172
    },
    "JOR": {
      "prob": 0.001,
      "change24h": null,
      "volume": 32808615
    },
    "CUW": {
      "prob": 0.001,
      "change24h": null,
      "volume": 43906253
    },
    "ARG": {
      "prob": 0.118,
      "change24h": null,
      "volume": 62894215
    },
    "GER": {
      "prob": 0.057,
      "change24h": -0.007,
      "volume": 59408834
    },
    "COL": {
      "prob": 0.015,
      "change24h": -0.001,
      "volume": 60763276
    },
    "IRN": {
      "prob": 0.001,
      "change24h": null,
      "volume": 58125712
    },
    "POR": {
      "prob": 0.069,
      "change24h": -0.004,
      "volume": 58892365
    },
    "GHA": {
      "prob": 0.001,
      "change24h": -0.001,
      "volume": 56672933
    },
    "NED": {
      "prob": 0.057,
      "change24h": 0.017,
      "volume": 58970023
    },
    "ALG": {
      "prob": 0.001,
      "change24h": null,
      "volume": 67026257
    },
    "BIH": {
      "prob": 0.001,
      "change24h": null,
      "volume": 46903972
    },
    "USA": {
      "prob": 0.04,
      "change24h": 0.007,
      "volume": 90838457
    },
    "CAN": {
      "prob": 0.004,
      "change24h": null,
      "volume": 64764908
    },
    "URU": {
      "prob": 0.006,
      "change24h": null,
      "volume": 62477096
    },
    "MEX": {
      "prob": 0.014,
      "change24h": 0.001,
      "volume": 80632743
    },
    "PAR": {
      "prob": 0.002,
      "change24h": null,
      "volume": 66135287
    },
    "SCO": {
      "prob": 0.002,
      "change24h": null,
      "volume": 63482925
    },
    "JPN": {
      "prob": 0.025,
      "change24h": 0.011,
      "volume": 68526222
    },
    "NOR": {
      "prob": 0.025,
      "change24h": null,
      "volume": 57978224
    },
    "ECU": {
      "prob": 0.002,
      "change24h": -0.003,
      "volume": 67606021
    },
    "UZB": {
      "prob": 0.001,
      "change24h": null,
      "volume": 61438993
    },
    "MAR": {
      "prob": 0.023,
      "change24h": -0.004,
      "volume": 64806351
    },
    "PAN": {
      "prob": 0.001,
      "change24h": null,
      "volume": 20039160
    },
    "IRQ": {
      "prob": 0.001,
      "change24h": null,
      "volume": 30408818
    },
    "RSA": {
      "prob": 0.001,
      "change24h": null,
      "volume": 39367545
    },
    "SEN": {
      "prob": 0.006,
      "change24h": null,
      "volume": 55224593
    },
    "CIV": {
      "prob": 0.006,
      "change24h": 0.001,
      "volume": 80070296
    },
    "COD": {
      "prob": 0.002,
      "change24h": null,
      "volume": 78016501
    },
    "CPV": {
      "prob": 0.001,
      "change24h": null,
      "volume": 50543119
    },
    "CZE": {
      "prob": 0.001,
      "change24h": null,
      "volume": 57374514
    },
    "QAT": {
      "prob": 0.001,
      "change24h": null,
      "volume": 45075300
    },
    "BEL": {
      "prob": 0.016,
      "change24h": null,
      "volume": 60916384
    },
    "AUS": {
      "prob": 0.003,
      "change24h": -0.001,
      "volume": 70892739
    },
    "KSA": {
      "prob": 0.001,
      "change24h": null,
      "volume": 56895456
    },
    "AUT": {
      "prob": 0.004,
      "change24h": -0.001,
      "volume": 61960185
    },
    "CRO": {
      "prob": 0.006,
      "change24h": -0.001,
      "volume": 66355042
    },
    "EGY": {
      "prob": 0.003,
      "change24h": 0.001,
      "volume": 73569106
    },
    "SWE": {
      "prob": 0.003,
      "change24h": -0.002,
      "volume": 54450532
    }
  }
}
